pm_attacher/__init__.py
pm_attacher/__main__.py
pm_attacher/database.py
pm_attacher/main.py
pm_attacher/options.py
pm_attacher/sql.py
pm_attacher-0.2.4.dist-info/entry_points.txt
pm_attacher-0.2.4.dist-info/WHEEL
pm_attacher-0.2.4.dist-info/METADATA
pm_attacher-0.2.4.dist-info/RECORD
