Metadata-Version: 2.1
Name: pm-attacher
Version: 0.2.4
Summary: Attach files to a patient's medical record (TrustMed)
Author: Vladislav Chmelyuk
Author-email: neimp@yandex.ru
Requires-Python: >=3.9,<4.0
Classifier: Programming Language :: Python :: 3
Classifier: Programming Language :: Python :: 3.9
Classifier: Programming Language :: Python :: 3.10
Requires-Dist: loguru (>=0.5.3,<0.6.0)
Requires-Dist: pymssql (>=2.2.2,<3.0.0)
Requires-Dist: typer (>=0.4.0,<0.5.0)
